marlin/__init__.py
marlin/exploration_client.py
marlin/marlin_batch_client.py
marlin/marlin_service_pb2.py
marlin/marlin_service_pb2_grpc.py
marlin/batch_store/__init__.py
marlin/batch_store/batch_store.py
marlin/batch_store/pandas/__init__.py
marlin/batch_store/pandas/pandas_fs_batch_store.py
marlin/batch_store/pandas/point_in_time_joiner.py
marlin/batch_store/pandas/utils.py
marlin/config/__init__.py
marlin/config/config_processor.py
marlin/metadata_store/__init__.py
marlin/metadata_store/marlin_metadata_store.py
marlin/utils/__init__.py
marlinfs-0.0.2.dist-info/LICENSE
marlinfs-0.0.2.dist-info/METADATA
marlinfs-0.0.2.dist-info/WHEEL
marlinfs-0.0.2.dist-info/top_level.txt
marlinfs-0.0.2.dist-info/RECORD
