Metadata-Version: 2.1
Name: marlinfs
Version: 0.0.2
Summary: Python Client for Marlin Feature Store
Home-page: https://github.com/marlin-fs/marlin-python-client
Author: Tern
Author-email: support@tern.ai
License: MIT
Project-URL: Bug Tracker, https://github.com/marlin-fs/marlin-python-client/issues
Project-URL: Documentation, https://docs.tern.ai/
Project-URL: Source Code, https://github.com/marlin-fs/marlin-python-client
Platform: UNKNOWN
Requires-Dist: grpcio-tools (==1.33.2)
Requires-Dist: grpcio (==1.33.2)
Requires-Dist: googleapis-common-protos (==1.52.0)
Requires-Dist: pyarrow (==1.0.1)
Requires-Dist: fsspec (==0.8.4)
Requires-Dist: pandas (==1.1.3)
Requires-Dist: s3fs (==0.5.1)
Requires-Dist: pytest (==6.1.1)
Requires-Dist: mock (==4.0.2)
Requires-Dist: pyrebase (==3.0.27)
Requires-Dist: numpy (==1.19.5)
